ip_db/__init__.py
ip_db/__version__.py
ip_db/database/__init__.py
ip_db/database/database.py
ip_db/database/maxmind_database.py
ip_db/database/tor_database.py
ip_db-0.0.1.dist-info/METADATA
ip_db-0.0.1.dist-info/RECORD
ip_db-0.0.1.dist-info/WHEEL
ip_db-0.0.1.dist-info/top_level.txt
