Metadata-Version: 2.1
Name: ip-db
Version: 0.0.1
Summary: A small Python 3 module to manage IP address databases used for resolving geolocation and getting threat information aboutIP address
Home-page: https://github.com/ipdbco/ip_db
Author: ipdbco_tuan
Author-email: 41750787+ipdbco@users.noreply.github.com
License: GNU GENERAL PUBLIC LICENSE
Requires-Dist: requests
Requires-Dist: maxminddb
